summarytools/__init__.py
summarytools/htmlwidgets.py
summarytools/summarytools.py
jupyter_summarytools-0.2.3.dist-info/LICENSE.txt
jupyter_summarytools-0.2.3.dist-info/METADATA
jupyter_summarytools-0.2.3.dist-info/WHEEL
jupyter_summarytools-0.2.3.dist-info/top_level.txt
jupyter_summarytools-0.2.3.dist-info/RECORD
